CONTRIBUTING.rst
HISTORY.rst
LICENSE
MANIFEST.in
README.rst
restart_app.py
setup.cfg
setup.py
kupfer_plugin_restart_app.egg-info/PKG-INFO
kupfer_plugin_restart_app.egg-info/SOURCES.txt
kupfer_plugin_restart_app.egg-info/dependency_links.txt
kupfer_plugin_restart_app.egg-info/not-zip-safe
kupfer_plugin_restart_app.egg-info/top_level.txt